baseline/__init__.py
baseline/cli.py
baseline/core.py
baseline_builder-1.7.1.dist-info/METADATA
baseline_builder-1.7.1.dist-info/WHEEL
baseline_builder-1.7.1.dist-info/entry_points.txt
baseline_builder-1.7.1.dist-info/top_level.txt
baseline_builder-1.7.1.dist-info/RECORD
