Metadata-Version: 2.1
Name: baseline-builder
Version: 1.7.1
Summary: Module for generating Baseline packages for deployment
Home-page: https://github.com/ripeda/Baseline-Builder
Author: RIPEDA Consulting
Author-email: info@ripeda.com
Classifier: Programming Language :: Python :: 3
Classifier: Operating System :: MacOS :: MacOS X
Requires-Python: >=3.6
Requires-Dist: macos-pkg-builder >=1.0.8
Requires-Dist: requests
